slupy/__init__.py
slupy/core/__init__.py
slupy/core/checks.py
slupy/core/conversions.py
slupy/core/helpers.py
slupy/data_wrangler/__init__.py
slupy/data_wrangler/dataset.py
slupy/data_wrangler/utils.py
slupy/dates/__init__.py
slupy/dates/constants.py
slupy/dates/functions.py
slupy/dates/time_conversions.py
slupy/dates/time_travel.py
slupy/dates/utils.py
slupy/decorators/__init__.py
slupy/decorators/decorators.py
slupy/email_ops/__init__.py
slupy/email_ops/email_ops.py
slupy/file_ops/__init__.py
slupy/file_ops/file_ops.py
slupy/mathematics/__init__.py
slupy/mathematics/mathematics.py
slupy/randomizer/__init__.py
slupy/randomizer/randomizer.py
slupy/strings/__init__.py
slupy/strings/strings.py
slupy/tests/__init__.py
slupy/tests/test_core.py
slupy/tests/test_dataset_class.py
slupy/tests/test_date_utils.py
slupy/tests/test_file_ops.py
slupy/tests/test_mathematics.py
slupy/tests/test_randomizer.py
slupy/tests/test_strings.py
slupy/tests/test_time_travel.py
slupy-5.0.dist-info/LICENSE
slupy-5.0.dist-info/METADATA
slupy-5.0.dist-info/WHEEL
slupy-5.0.dist-info/top_level.txt
slupy-5.0.dist-info/RECORD
