Metadata-Version: 2.1
Name: slupy
Version: 5.0
Summary: Library that serves a variety of utility/helper functionality (in Python) built on the standard library.
Home-page: https://github.com/Nishant173/slupy
Author: Nishant Rao
Author-email: nishant.rao173@gmail.com
License: MIT
Classifier: Development Status :: 5 - Production/Stable
Classifier: Intended Audience :: Developers
Classifier: License :: OSI Approved :: ISC License (ISCL)
Classifier: Natural Language :: English
Classifier: Programming Language :: Python :: 3.7
Classifier: Operating System :: Unix
Classifier: Operating System :: MacOS :: MacOS X
Classifier: Operating System :: Microsoft :: Windows
License-File: LICENSE
